pymediumapi/__init__.py
pymediumapi-0.0.2.dist-info/LICENSE.md
pymediumapi-0.0.2.dist-info/METADATA
pymediumapi-0.0.2.dist-info/WHEEL
pymediumapi-0.0.2.dist-info/top_level.txt
pymediumapi-0.0.2.dist-info/RECORD
