Metadata-Version: 2.1
Name: pymediumapi
Version: 0.0.2
Summary: A python package to interact with Medium API
Home-page: https://github.com/andregri/pymediumapi
Author: Andrea Grillo
Author-email: andrea.grillo96@live.com
License: UNKNOWN
Project-URL: Bug Tracker, https://github.com/andregri/pymediumapi/issues
Platform: UNKNOWN
Classifier: Programming Language :: Python :: 3
Classifier: License :: OSI Approved :: Apache Software License
Classifier: Operating System :: OS Independent
Requires-Python: >=3.6
License-File: LICENSE.md
Requires-Dist: requests (==2.26.0)
